mcp_mongodb_bio_invasion/__init__.py
mcp_mongodb_bio_invasion/mcp_mongodb_server.py
mcp_mongodb_bio_invasion-0.1.1.dist-info/licenses/LICENSE
mcp_mongodb_bio_invasion-0.1.1.dist-info/METADATA
mcp_mongodb_bio_invasion-0.1.1.dist-info/WHEEL
mcp_mongodb_bio_invasion-0.1.1.dist-info/entry_points.txt
mcp_mongodb_bio_invasion-0.1.1.dist-info/top_level.txt
mcp_mongodb_bio_invasion-0.1.1.dist-info/RECORD
