Metadata-Version: 2.4
Name: mcp-mongodb-bio-invasion
Version: 0.1.1
Summary: MongoDB生物入侵研究MCP服务器 - 自然语言查询工具
Author-email: Your Name <your.email@example.com>
License: MIT
Keywords: mcp,mongodb,bio-invasion,nlp,vector-search
Classifier: Development Status :: 4 - Beta
Classifier: Intended Audience :: Science/Research
Classifier: License :: OSI Approved :: MIT License
Classifier: Programming Language :: Python :: 3.13
Classifier: Topic :: Scientific/Engineering :: Bio-Informatics
Classifier: Topic :: Database :: Database Engines/Servers
Classifier: Topic :: Scientific/Engineering :: Artificial Intelligence
Requires-Python: >=3.13
License-File: LICENSE
Requires-Dist: mcp[cli]>=1.13.1
Requires-Dist: pymongo>=4.6.0
Requires-Dist: python-dotenv>=1.0.0
Requires-Dist: transformers>=4.37.0
Requires-Dist: torch>=2.1.0
Requires-Dist: requests>=2.31.0
Dynamic: license-file
